denspa/__init__.py
denspa/vector_search.py
denspa/dense/__init__.py
denspa/dense/faiss/__init__.py
denspa/dense/faiss/faiss_api.py
denspa/sparse/__init__.py
denspa/sparse/doc_store.py
denspa/sparse/bm25/__init__.py
denspa/sparse/bm25/bm25.py
denspa/sparse/bm25/bm25_api.py
denspa/tokenizer/__init__.py
denspa/tokenizer/tokenizer.py
denspa-0.0.7.dist-info/licenses/LICENSE
denspa-0.0.7.dist-info/METADATA
denspa-0.0.7.dist-info/WHEEL
denspa-0.0.7.dist-info/top_level.txt
denspa-0.0.7.dist-info/RECORD
