Metadata-Version: 2.4
Name: DenSpa
Version: 0.0.7
Summary: DenSpa is an open-source package designed for hybrid search, enabling seamless integration into RAG frameworks.
Author: Ivan Kankeu
License-Expression: MIT
Project-URL: Homepage, https://github.com/Kankeu/denspa
Project-URL: Issues, https://github.com/Kankeu/denspa/issues
Keywords: hybrid search,semantic search,keyword search,vector search,FAISS BM25,LangChain
Classifier: Programming Language :: Python :: 3
Classifier: Operating System :: OS Independent
Requires-Python: >=3.10
License-File: LICENSE
Requires-Dist: langchain>=0.3.16
Requires-Dist: faiss-cpu>=1.10.0
Requires-Dist: nltk>=3.9.1
Requires-Dist: scikit-learn>=1.6.1
Requires-Dist: numpy<=1.26.4
Requires-Dist: scipy>=1.15.1
Requires-Dist: spacy>=3.5.2
Dynamic: license-file
